pytest_ignore_flaky/__init__.py
pytest_ignore_flaky-2.2.1.dist-info/LICENSE
pytest_ignore_flaky-2.2.1.dist-info/METADATA
pytest_ignore_flaky-2.2.1.dist-info/WHEEL
pytest_ignore_flaky-2.2.1.dist-info/entry_points.txt
pytest_ignore_flaky-2.2.1.dist-info/top_level.txt
pytest_ignore_flaky-2.2.1.dist-info/RECORD
